cm_shared_generator/Shared_Generator.py
cm_shared_generator/__init__.py
tests/UT_Shared_Generator.py
tests/__init__.py
cm_shared_generator-0.1.4.dist-info/LICENSE.txt
cm_shared_generator-0.1.4.dist-info/METADATA
cm_shared_generator-0.1.4.dist-info/WHEEL
cm_shared_generator-0.1.4.dist-info/top_level.txt
cm_shared_generator-0.1.4.dist-info/RECORD
