Metadata-Version: 2.1
Name: cm-shared-generator
Version: 0.1.4
Summary: Shared generator between process
Home-page: https://gitlab.com/Juquod/cm_shared_generator
Author: Célien Menneteau
Author-email: celien.menneteau@gmail.com
License: UNKNOWN
Platform: UNKNOWN
Classifier: Programming Language :: Python :: 3
Classifier: License :: OSI Approved :: Apache Software License
Classifier: Operating System :: Unix
Requires-Python: >=3.6
